beancount_import/__init__.py
beancount_import/amount_parsing.py
beancount_import/amount_parsing_test.py
beancount_import/delete_transactions.py
beancount_import/journal_editor.py
beancount_import/journal_editor_test.py
beancount_import/list_balance_at_date.py
beancount_import/matching.py
beancount_import/matching_test.py
beancount_import/posting_date.py
beancount_import/reconcile.py
beancount_import/reconcile_test.py
beancount_import/remove_transfer_account.py
beancount_import/rename_account.py
beancount_import/sorted_entry_printer.py
beancount_import/sorted_list.py
beancount_import/test_util.py
beancount_import/thread_helpers.py
beancount_import/training.py
beancount_import/training_test.py
beancount_import/unbook.py
beancount_import/unbook_test.py
beancount_import/webserver.py
beancount_import/webserver_test.py
beancount_import/frontend_dist/app.css
beancount_import/frontend_dist/app.js
beancount_import/frontend_dist/app.js.map
beancount_import/frontend_dist/index.html
beancount_import/source/__init__.py
beancount_import/source/amazon.py
beancount_import/source/amazon_invoice.py
beancount_import/source/amazon_invoice_sanitize.py
beancount_import/source/amazon_invoice_test.py
beancount_import/source/amazon_test.py
beancount_import/source/description_based_source.py
beancount_import/source/description_based_source_test.py
beancount_import/source/generic_importer_source.py
beancount_import/source/generic_importer_source_test.py
beancount_import/source/google_purchases.py
beancount_import/source/google_purchases_sanitize.py
beancount_import/source/google_purchases_test.py
beancount_import/source/healthequity.py
beancount_import/source/healthequity_test.py
beancount_import/source/link_based_source.py
beancount_import/source/mint.py
beancount_import/source/mint_test.py
beancount_import/source/ofx.py
beancount_import/source/ofx_sanitize.py
beancount_import/source/ofx_test.py
beancount_import/source/paypal.py
beancount_import/source/paypal_sanitize.py
beancount_import-1.4.0.dist-info/LICENSE
beancount_import-1.4.0.dist-info/METADATA
beancount_import-1.4.0.dist-info/WHEEL
beancount_import-1.4.0.dist-info/top_level.txt
beancount_import-1.4.0.dist-info/RECORD
