Metadata-Version: 2.1
Name: beancount-import
Version: 1.4.0
Summary: Semi-automatic importing of external data into beancount.
Home-page: https://github.com/jbms/beancount-import
Author: Jeremy Maitin-Shepard
Author-email: jeremy@jeremyms.com
License: GPLv2
Platform: UNKNOWN
Requires-Python: >=3.8
License-File: LICENSE
Requires-Dist: beancount >=2.1.3
Requires-Dist: tornado
Requires-Dist: numpy
Requires-Dist: scipy
Requires-Dist: scikit-learn ~=1.2
Requires-Dist: nltk
Requires-Dist: python-dateutil
Requires-Dist: atomicwrites >=1.3.0
Requires-Dist: jsonschema
Requires-Dist: watchdog
Requires-Dist: typing-extensions
Requires-Dist: cachetools
